palestine_function_unit/__init__.py
palestine_function_unit/cli.py
palestine_function_unit/core.py
palestine_function_unit/units.py
palestine_function_unit-1.33.dist-info/METADATA
palestine_function_unit-1.33.dist-info/WHEEL
palestine_function_unit-1.33.dist-info/entry_points.txt
palestine_function_unit-1.33.dist-info/top_level.txt
palestine_function_unit-1.33.dist-info/RECORD
