Metadata-Version: 2.1
Name: palestine-function-unit
Version: 1.33
Summary: P-Unit Converter based on recursive persistence and geometric scaling
Home-page: https://github.com/ileathan/punit 
Author: Palestine Equation
Author-email: 1@leat.xyz
License: UNKNOWN
Platform: UNKNOWN
Classifier: Programming Language :: Python :: 3
Classifier: License :: OSI Approved :: MIT License
Classifier: Operating System :: OS Independent
